pyqt_polygon_window/__init__.py
pyqt_polygon_window/polygonWindow.py
pyqt_polygon_window/ico/__init__.py
pyqt_polygon_window/ico/close.png
pyqt_polygon_window/style/__init__.py
pyqt_polygon_window/style/button.css
pyqt_polygon_window-0.0.1.dist-info/LICENSE
pyqt_polygon_window-0.0.1.dist-info/METADATA
pyqt_polygon_window-0.0.1.dist-info/WHEEL
pyqt_polygon_window-0.0.1.dist-info/top_level.txt
pyqt_polygon_window-0.0.1.dist-info/RECORD
